{"github://viscaelfan/sobages":{"assets/images/logo3-85x85.png":"nrRvmTV3B5N5dr8q7E5F6g==","assets/images/hashes.json":"lRxjrlH7P5Zs7xLPK6tdkw==","assets/images/tremola-client-so-bages1-original-2.png":"38Z4W1xkyraOvWSpjUpUsA==","assets/images/features3.jpg":"HUfpc9SvDwBk7sbVG2SgiA==","assets/images/1514cd9565ec18cdab04f26deb15ff14-816x816.png":"WUuhUi13T/10TanF3veDlw==","assets/images/logo-embleme-f-web-2-816x338.jpeg":"M/49/ZYsGryw15PfL9X2Pw==","assets/images/background3.jpg":"Vb7GgbMoe0curpGYBParsg==","assets/images/background5.jpg":"IR50eEAa/gjv9e3Jv2cWTg==","assets/images/background8.jpg":"911X7bM4yT2Mobv6BsMc+g==","assets/images/14-006-sobages-p1010271-972x653.jpg":"CnySEuCdv3sixqd9rdGnsQ==","assets/bootstrap/css/bootstrap-grid.min.css":"4bnuDDTauYpkcZNhkYKtrg==","assets/bootstrap/css/bootstrap.min.css":"qGiBfMEZYUPQ8GJUeqipZw==","assets/bootstrap/css/bootstrap-reboot.min.css":"/iLrQLzPIC+HbKPQfUweBg==","assets/smoothscroll/smooth-scroll.js":"I6Cnt5FZXvE7AwxKBjLHIw==","assets/theme/css/style.css":"n7PKsNMLbou5LeKopzBX3Q==-VITbTf54ezV7Z7I/e4lZVw==","assets/bootstrap/js/bootstrap.bundle.min.js":"4jB/FPBUKrTUyehEkinqIg==","assets/ytplayer/index.js":"m99qxtkghzQa/qd3oHC+KA==","assets/dropdown/css/style.css":"Vb8nb3PvfIj5jIp56aQkiA==","assets/dropdown/js/navbar-dropdown.js":"+zsyY+Azav1PQJWv8lLucw==","assets/socicon/css/styles.css":"yjHs7tV2SewoW36KZ0bi9w==","assets/socicon/fonts/socicon.eot":"MvYQV8XxgngrhGqjN3oHBw==","assets/socicon/fonts/socicon.ttf":"IyAo3XNB2a/Q0ml3ZraPsQ==","assets/socicon/fonts/socicon.svg":"U1iRKoyNjKeR+mUJr3QbXg==","assets/socicon/fonts/socicon.woff":"zQDjXd6bBUQi87pRsBWVqQ==","assets/web/assets/mobirise-icons2/mobirise2.css":"+RO7OxVtE1FsD/N7V3/ADw==","assets/socicon/fonts/socicon.woff2":"o3w8h99EHOwP99NXAoHpOQ==","assets/web/assets/mobirise-icons2/mobirise2.eot":"B2EjryGRojlTpzr1GHt3LQ==","assets/web/assets/mobirise-icons2/mobirise2.svg":"usCYAy7QdzckfeGReb9wWQ==","assets/web/assets/mobirise-icons2/mobirise2.ttf":"VMdAr7YYQ2ab9KiUyabAGA==","assets/web/assets/mobirise-icons2/mobirise2.woff":"xY3InaTfYGp0nlCuQBMudQ=="}}